fileio_upload/__init__.py
fileio_upload/exceptions.py
fileio_upload/fileio.py
fileio_upload-1.2.1.dist-info/LICENCE
fileio_upload-1.2.1.dist-info/METADATA
fileio_upload-1.2.1.dist-info/WHEEL
fileio_upload-1.2.1.dist-info/top_level.txt
fileio_upload-1.2.1.dist-info/RECORD
