Metadata-Version: 2.1
Name: fileio-upload
Version: 1.2.1
Summary: Upload Your Files to File.io
Author-email: Mji DarkPwn <mogtabaemile244566@gmail.com>
Project-URL: Homepage, https://github.com/c4ssif3r/fileio_upload
Project-URL: Bug Tracker, https://github.com/c4ssif3r/fileio_upload/issues
Classifier: Programming Language :: Python :: 3
Classifier: License :: OSI Approved :: MIT License
Classifier: Operating System :: OS Independent
Requires-Python: >=3.7
License-File: LICENCE
